{
  "@context": "http://schema.org",
  "@type": "Place",
  "additionalProperty": {
    "@type": "PropertyValue",
    "name": "id",
    "value": 152418
  },
  "name": "ALVERTA GREEN MUSEUM",
  "address": {
    "@type": "PostalAddress",
    "streetAddress": "207 W CHURCH ST",
    "addressLocality": "MASON",
    "addressRegion": "OH",
    "addressCountry": "United States",
    "postalCode": "45040"
  },
  "hasMap": "http://www.openstreetmap.org/?mlat=39.3614&mlon=-84.3111#map=15/39.3614/-84.3111",
  "geo": {
    "@type": "GeoCoordinates",
    "latitude": 39.3614,
    "longitude": -84.3111
  },
  "url": "http://www.historicalmason.homestead.com",
  "telephone": "+1 (513) 398-6750",
  "contactPoint": [

  ],
  "mainEntityOfPage": {
    "@Type": "Dataset",
    "id": "8403900195",
    "name": "us",
    "url": "http://www.imls.gov",
    "license": "http://creativecommons.org/licenses/by-sa/4.0/"
  }
}