{
  "@context": "http://schema.org",
  "@type": "Place",
  "additionalProperty": {
    "@type": "PropertyValue",
    "name": "id",
    "value": 158320
  },
  "name": [
    {
      "@value": "SALEM ARCHIVES AND HISTORICAL RESEARCH CENTER OF ROSEHILL IN",
      "@language": "en"
    }
  ],
  "address": {
    "@type": "PostalAddress",
    "streetAddress": "22735 LUTHERAN CHURCH RD",
    "addressLocality": "TOMBALL",
    "addressRegion": "TX",
    "addressCountry": "United States",
    "postalCode": "77377"
  },
  "hasMap": "http://www.openstreetmap.org/?mlat=30.0927&mlon=-95.6701#map=15/30.0927/-95.6701",
  "geo": {
    "@type": "GeoCoordinates",
    "latitude": 30.0927,
    "longitude": -95.6701
  },
  "mainEntityOfPage": {
    "@Type": "Dataset",
    "id": "8404800420",
    "name": "us",
    "url": "http://www.imls.gov",
    "license": "http://creativecommons.org/licenses/by-sa/4.0/"
  }
}