{
  "@context": "http://schema.org",
  "@type": "Place",
  "additionalProperty": {
    "@type": "PropertyValue",
    "name": "id",
    "value": 158417
  },
  "name": [
    {
      "@value": "GRIFFITH HOME PLACE MUSEUM AND RESEARCH CENTER INC",
      "@langauge": "en"
    }
  ],
  "address": {
    "@type": "PostalAddress",
    "streetAddress": "803 FIRST ST",
    "addressLocality": "TERRELL",
    "addressRegion": "TX",
    "addressCountry": "United States",
    "postalCode": "75160-7516"
  },
  "hasMap": "http://www.openstreetmap.org/?mlat=32.7425&mlon=-96.2832#map=15/32.7425/-96.2832",
  "geo": {
    "@type": "GeoCoordinates",
    "latitude": 32.7425,
    "longitude": -96.2832
  },
  "telephone": "+1 (972) 563-6536",
  "mainEntityOfPage": {
    "@Type": "Dataset",
    "id": "8404800517",
    "name": "us",
    "url": "http://www.imls.gov",
    "license": "http://creativecommons.org/licenses/by-sa/4.0/"
  }
}