{
  "@context": "http://schema.org",
  "@type": "Place",
  "additionalProperty": {
    "@type": "PropertyValue",
    "name": "id",
    "value": 158662
  },
  "name": "GORGE PRESERVATION SOCIETY",
  "address": {
    "@type": "PostalAddress",
    "streetAddress": "2075 FM 2673",
    "addressLocality": "CANYON LAKE",
    "addressRegion": "TX",
    "addressCountry": "United States",
    "postalCode": "78133-4786"
  },
  "hasMap": "http://www.openstreetmap.org/?mlat=29.8461&mlon=-98.1816#map=15/29.8461/-98.1816",
  "geo": {
    "@type": "GeoCoordinates",
    "latitude": 29.8461,
    "longitude": -98.1816
  },
  "telephone": "+1 (830) 964-6465",
  "contactPoint": [

  ],
  "mainEntityOfPage": {
    "@Type": "Dataset",
    "id": "8404800762",
    "name": "us",
    "url": "http://www.imls.gov",
    "license": "http://creativecommons.org/licenses/by-sa/4.0/"
  }
}