{
  "@context": "http://schema.org",
  "@type": "Place",
  "additionalProperty": {
    "@type": "PropertyValue",
    "name": "id",
    "value": 158996
  },
  "name": "BORDER PATROL MUSEUM & MEMORIAL LIBRARY FOUNDATION",
  "address": {
    "@type": "PostalAddress",
    "streetAddress": "4315 WOODROW BEAN",
    "addressLocality": "EL PASO",
    "addressRegion": "TX",
    "addressCountry": "United States",
    "postalCode": "79924"
  },
  "hasMap": "http://www.openstreetmap.org/?mlat=31.9025&mlon=-106.449#map=15/31.9025/-106.449",
  "geo": {
    "@type": "GeoCoordinates",
    "latitude": 31.9025,
    "longitude": -106.449
  },
  "url": "http://www.borderpatrolmuseum.com",
  "telephone": "+1 (915) 759-6060",
  "contactPoint": [

  ],
  "mainEntityOfPage": {
    "@Type": "Dataset",
    "id": "8404801096",
    "name": "us",
    "url": "http://www.imls.gov",
    "license": "http://creativecommons.org/licenses/by-sa/4.0/"
  }
}