{
  "@context": "http://schema.org",
  "@type": "Place",
  "additionalProperty": {
    "@type": "PropertyValue",
    "name": "id",
    "value": 131229
  },
  "name": [
    {
      "@value": "GASLAMP BLACK HISTORICAL SOCIETY",
      "@language": "en"
    }
  ],
  "address": {
    "@type": "PostalAddress",
    "streetAddress": "BOX 122469",
    "addressLocality": "SAN DIEGO",
    "addressRegion": "CA",
    "addressCountry": "United States",
    "postalCode": "92112-2469"
  },
  "hasMap": "http://www.openstreetmap.org/?mlat=32.7148&mlon=-117.157#map=15/32.7148/-117.157",
  "geo": {
    "@type": "GeoCoordinates",
    "latitude": 32.7148,
    "longitude": -117.157
  },
  "mainEntityOfPage": {
    "@Type": "Dataset",
    "id": "8400601355",
    "name": "us",
    "url": "http://www.imls.gov",
    "license": "http://creativecommons.org/licenses/by-sa/4.0/"
  }
}