{
  "@context": "http://schema.org",
  "@type": "Place",
  "additionalProperty": {
    "@type": "PropertyValue",
    "name": "id",
    "value": 156970
  },
  "name": "THE OCONEE COUNTY MUSEUM ASSOCIATION",
  "address": {
    "@type": "PostalAddress",
    "streetAddress": "211 W SOUTH 1ST STREET",
    "addressLocality": "SENECA",
    "addressRegion": "SC",
    "addressCountry": "United States",
    "postalCode": "29678"
  },
  "hasMap": "http://www.openstreetmap.org/?mlat=34.6832&mlon=-82.9572#map=15/34.6832/-82.9572",
  "geo": {
    "@type": "GeoCoordinates",
    "latitude": 34.6832,
    "longitude": -82.9572
  },
  "url": "http://lunneyhousemuseum.org",
  "contactPoint": [

  ],
  "mainEntityOfPage": {
    "@Type": "Dataset",
    "id": "8404500265",
    "name": "us",
    "url": "http://www.imls.gov",
    "license": "http://creativecommons.org/licenses/by-sa/4.0/"
  }
}