{
  "@context": "http://schema.org",
  "@type": "Place",
  "additionalProperty": {
    "@type": "PropertyValue",
    "name": "id",
    "value": 128834
  },
  "name": [
    {
      "@value": "PICKENS COUNTY TOURISM ASSOCIATION",
      "@langauge": "en"
    }
  ],
  "address": {
    "@type": "PostalAddress",
    "streetAddress": "PO BOX 417",
    "addressLocality": "CARROLLTON",
    "addressRegion": "AL",
    "addressCountry": "United States",
    "postalCode": "35447-0417"
  },
  "hasMap": "http://www.openstreetmap.org/?mlat=33.2741&mlon=-88.1531#map=15/33.2741/-88.1531",
  "geo": {
    "@type": "GeoCoordinates",
    "latitude": 33.2741,
    "longitude": -88.1531
  },
  "telephone": "+1 (205) 367-2186",
  "mainEntityOfPage": {
    "@Type": "Dataset",
    "id": "8400100364",
    "name": "us",
    "url": "http://www.imls.gov",
    "license": "http://creativecommons.org/licenses/by-sa/4.0/"
  }
}