{
  "@context": "http://schema.org",
  "@type": "Place",
  "additionalProperty": {
    "@type": "PropertyValue",
    "name": "id",
    "value": 129258
  },
  "name": "NAVAJO CODE TALKERS FOUNDATION",
  "address": {
    "@type": "PostalAddress",
    "streetAddress": "PO BOX 1266",
    "addressLocality": "WINDOW ROCK",
    "addressRegion": "AZ",
    "addressCountry": "United States",
    "postalCode": "86515-1266"
  },
  "hasMap": "http://www.openstreetmap.org/?mlat=35.6779&mlon=-109.054#map=15/35.6779/-109.054",
  "geo": {
    "@type": "GeoCoordinates",
    "latitude": 35.6779,
    "longitude": -109.054
  },
  "url": "http://navajocodetalkers.org/",
  "contactPoint": [

  ],
  "mainEntityOfPage": {
    "@Type": "Dataset",
    "id": "8400400160",
    "name": "us",
    "url": "http://www.imls.gov",
    "license": "http://creativecommons.org/licenses/by-sa/4.0/"
  }
}