{
  "@context": "http://schema.org",
  "@type": "Place",
  "additionalProperty": {
    "@type": "PropertyValue",
    "name": "id",
    "value": 185115
  },
  "name": [
    {
      "@value": "Kompero Museum",
      "@langauge": "en"
    }
  ],
  "address": {
    "@type": "PostalAddress",
    "addressCountry": "Finland"
  },
  "url": "http://www.komperonmuseo.fi",
  "mainEntityOfPage": {
    "@Type": "Dataset",
    "name": "fi",
    "url": "http://www.museums.io/en/museums/185115",
    "license": "http://creativecommons.org/licenses/by-sa/4.0/"
  }
}