{
  "@context": "http://schema.org",
  "@type": "Place",
  "additionalProperty": {
    "@type": "PropertyValue",
    "name": "id",
    "value": 185489
  },
  "name": [
    {
      "@value": "Bank of Finland Museum",
      "@language": "en"
    }
  ],
  "address": {
    "@type": "PostalAddress",
    "addressCountry": "Finland"
  },
  "hasMap": "http://www.openstreetmap.org/?mlat=24.9533&mlon=24.9533#map=15/24.9533/24.9533",
  "geo": {
    "@type": "GeoCoordinates",
    "latitude": 24.9533,
    "longitude": 24.9533
  },
  "url": "http://www.rahamuseo.fi",
  "mainEntityOfPage": {
    "@Type": "Dataset",
    "name": "fi",
    "url": "http://www.museums.io/en/museums/185489",
    "license": "http://creativecommons.org/licenses/by-sa/4.0/"
  }
}