{
  "@context": "http://schema.org",
  "@type": "Place",
  "additionalProperty": {
    "@type": "PropertyValue",
    "name": "id",
    "value": 185978
  },
  "name": [
    {
      "@value": "Museo civico garibaldino e risorgimentale",
      "@langauge": "it"
    }
  ],
  "address": {
    "@type": "PostalAddress",
    "streetAddress": "Piazza Angiulli, 7 , ",
    "addressLocality": "Santa Maria Capua Vetere",
    "addressRegion": "Campania",
    "addressCountry": "Italy"
  },
  "hasMap": "http://www.openstreetmap.org/?mlat=41.0781&mlon=14.2658#map=15/41.0781/14.2658",
  "geo": {
    "@type": "GeoCoordinates",
    "latitude": 41.0781,
    "longitude": 14.2658
  },
  "telephone": "+39 0823813211",
  "photo": {
    "@type": "ImageObject",
    "contentUrl": "http://images.museums.io/Gp5o2joPbWF8RaIx9c7f4J3P48E=/1000x1000/museums/logos/000/185/978/original/a1762b443424a533c6f46b5b14bb717ce264ff.jpg"
  },
  "mainEntityOfPage": {
    "@Type": "Dataset",
    "id": "101818",
    "name": "itapi",
    "url": "http://www.beniculturali.it/mibac/export/MiBAC/sito-MiBAC/MenuPrincipale/Trasparenza/Open-Data/",
    "license": "http://creativecommons.org/licenses/by-sa/3.0/deed.it"
  }
}