{
  "@context": "http://schema.org",
  "@type": "Place",
  "additionalProperty": {
    "@type": "PropertyValue",
    "name": "id",
    "value": 157263
  },
  "name": "GREAT PLAINS NATIVE PLANT SOCIETY",
  "address": {
    "@type": "PostalAddress",
    "streetAddress": "PO BOX 461",
    "addressLocality": "HOT SPRINGS",
    "addressRegion": "SD",
    "addressCountry": "United States",
    "postalCode": "57747-0461"
  },
  "hasMap": "http://www.openstreetmap.org/?mlat=43.4261&mlon=-103.481#map=15/43.4261/-103.481",
  "geo": {
    "@type": "GeoCoordinates",
    "latitude": 43.4261,
    "longitude": -103.481
  },
  "url": "http://www.gpnps.org/",
  "telephone": "+1 (605) 745-3397",
  "contactPoint": [

  ],
  "mainEntityOfPage": {
    "@Type": "Dataset",
    "id": "8404600148",
    "name": "us",
    "url": "http://www.imls.gov",
    "license": "http://creativecommons.org/licenses/by-sa/4.0/"
  }
}