{
  "@context": "http://schema.org",
  "@type": "Place",
  "additionalProperty": {
    "@type": "PropertyValue",
    "name": "id",
    "value": 141396
  },
  "name": [
    {
      "@value": "FRIENDS OF PEARYS EAGLE ISLAND LTD",
      "@langauge": "en"
    }
  ],
  "address": {
    "@type": "PostalAddress",
    "streetAddress": "PO BOX 70",
    "addressLocality": "BAILEY ISLAND",
    "addressRegion": "ME",
    "addressCountry": "United States",
    "postalCode": "04003-0070"
  },
  "hasMap": "http://www.openstreetmap.org/?mlat=43.736&mlon=-69.9951#map=15/43.736/-69.9951",
  "geo": {
    "@type": "GeoCoordinates",
    "latitude": 43.736,
    "longitude": -69.9951
  },
  "mainEntityOfPage": {
    "@Type": "Dataset",
    "id": "8402300245",
    "name": "us",
    "url": "http://www.imls.gov",
    "license": "http://creativecommons.org/licenses/by-sa/4.0/"
  }
}