{
  "@context": "http://schema.org",
  "@type": "Place",
  "additionalProperty": {
    "@type": "PropertyValue",
    "name": "id",
    "value": 141533
  },
  "name": [
    {
      "@value": "MAINE JEWISH MUSEUM",
      "@langauge": "en"
    }
  ],
  "address": {
    "@type": "PostalAddress",
    "streetAddress": "267 CONGRESS ST",
    "addressLocality": "PORTLAND",
    "addressRegion": "ME",
    "addressCountry": "United States",
    "postalCode": "04101-3611"
  },
  "hasMap": "http://www.openstreetmap.org/?mlat=43.6622&mlon=-70.2524#map=15/43.6622/-70.2524",
  "geo": {
    "@type": "GeoCoordinates",
    "latitude": 43.6622,
    "longitude": -70.2524
  },
  "url": "http://www.mainejewishmuseum.org",
  "telephone": "+1 (207) 329-9854",
  "mainEntityOfPage": {
    "@Type": "Dataset",
    "id": "8402300382",
    "name": "us",
    "url": "http://www.imls.gov",
    "license": "http://creativecommons.org/licenses/by-sa/4.0/"
  }
}