{
  "@context": "http://schema.org",
  "@type": "Place",
  "additionalProperty": {
    "@type": "PropertyValue",
    "name": "id",
    "value": 154014
  },
  "name": [
    {
      "@value": "ELDORADO HISTORICAL SOCIETY INC",
      "@language": "en"
    }
  ],
  "address": {
    "@type": "PostalAddress",
    "streetAddress": "PO BOX340",
    "addressLocality": "ELDORADO",
    "addressRegion": "OK",
    "addressCountry": "United States",
    "postalCode": "73537-0340"
  },
  "hasMap": "http://www.openstreetmap.org/?mlat=34.4731&mlon=-99.6482#map=15/34.4731/-99.6482",
  "geo": {
    "@type": "GeoCoordinates",
    "latitude": 34.4731,
    "longitude": -99.6482
  },
  "mainEntityOfPage": {
    "@Type": "Dataset",
    "id": "8404000368",
    "name": "us",
    "url": "http://www.imls.gov",
    "license": "http://creativecommons.org/licenses/by-sa/4.0/"
  }
}