{
  "@context": "http://schema.org",
  "@type": "Place",
  "additionalProperty": {
    "@type": "PropertyValue",
    "name": "id",
    "value": 162497
  },
  "name": "OGLEBAY FOUNDATION",
  "address": {
    "@type": "PostalAddress"
  },
  "hasMap": "http://www.openstreetmap.org/?mlat=40.0694&mlon=-80.6878#map=15/40.0694/-80.6878",
  "geo": {
    "@type": "GeoCoordinates",
    "latitude": 40.0694,
    "longitude": -80.6878
  },
  "contactPoint": [

  ],
  "mainEntityOfPage": {
    "@Type": "Dataset",
    "id": "8405400210",
    "name": "us",
    "url": "http://www.imls.gov",
    "license": "http://creativecommons.org/licenses/by-sa/4.0/"
  }
}