{
  "@context": "http://schema.org",
  "@type": "Place",
  "additionalProperty": {
    "@type": "PropertyValue",
    "name": "id",
    "value": 184852
  },
  "name": [
    {
      "@value": "Klerksdorp Museums",
      "@language": "en"
    }
  ],
  "address": {
    "@type": "PostalAddress",
    "streetAddress": "Cnr Margaretha Prinsloo & Lombard Streets, Klerksdorp",
    "addressLocality": "Klerksdorp",
    "addressRegion": "NW Province",
    "addressCountry": "South Africa"
  },
  "telephone": "018 487 8900",
  "mainEntityOfPage": {
    "@Type": "Dataset",
    "name": "sa",
    "url": "http://www.museums.io/en/museums/184852",
    "license": "http://creativecommons.org/licenses/by-sa/4.0/"
  }
}