{
  "@context": "http://schema.org",
  "@type": "Place",
  "additionalProperty": {
    "@type": "PropertyValue",
    "name": "id",
    "value": 183176
  },
  "name": [
    {
      "@value": "Bergbaumuseum Maffeischächte",
      "@langauge": "en"
    }
  ],
  "address": {
    "@type": "PostalAddress",
    "streetAddress": "Nitzlbuch",
    "addressLocality": "Auerbach",
    "addressRegion": "Oberpfalz",
    "addressCountry": "Germany",
    "postalCode": "91275"
  },
  "hasMap": "http://www.openstreetmap.org/?mlat=49.6797&mlon=11.6495#map=15/49.6797/11.6495",
  "geo": {
    "@type": "GeoCoordinates",
    "latitude": 49.6797,
    "longitude": 11.6495
  },
  "url": "http://www.maffeispiele.de",
  "telephone": "09624/2049573",
  "mainEntityOfPage": {
    "@Type": "Dataset",
    "name": "de_bavaria",
    "url": "http://www.museums.io/en/museums/183176",
    "license": "http://creativecommons.org/licenses/by-sa/4.0/"
  }
}