{
  "@context": "http://schema.org",
  "@type": "Place",
  "additionalProperty": {
    "@type": "PropertyValue",
    "name": "id",
    "value": 144780
  },
  "name": "LAKE SUPERIOR ZOO AMERICAN ASSOCIATION OF ZOO KEEPERS CHAPTER",
  "address": {
    "@type": "PostalAddress",
    "streetAddress": "7210 FREMONT STREET",
    "addressLocality": "DULUTH",
    "addressRegion": "MN",
    "addressCountry": "United States",
    "postalCode": "55807"
  },
  "hasMap": "http://www.openstreetmap.org/?mlat=46.7262&mlon=-92.1896#map=15/46.7262/-92.1896",
  "geo": {
    "@type": "GeoCoordinates",
    "latitude": 46.7262,
    "longitude": -92.1896
  },
  "url": "http://www.aazk.org",
  "telephone": "+1 (218) 730-4900",
  "contactPoint": [

  ],
  "mainEntityOfPage": {
    "@Type": "Dataset",
    "id": "8402700220",
    "name": "us",
    "url": "http://www.imls.gov",
    "license": "http://creativecommons.org/licenses/by-sa/4.0/"
  }
}