{
  "@context": "http://schema.org",
  "@type": "Place",
  "additionalProperty": {
    "@type": "PropertyValue",
    "name": "id",
    "value": 189788
  },
  "name": "CRATERS OF THE MOON NATIONAL MONUMENT",
  "address": {
    "@type": "PostalAddress",
    "streetAddress": "P.O. BOX 29",
    "addressLocality": "ARCO",
    "addressRegion": "ID",
    "addressCountry": "United States",
    "postalCode": "83213"
  },
  "hasMap": "http://www.openstreetmap.org/?mlat=43.6328&mlon=-113.306#map=15/43.6328/-113.306",
  "geo": {
    "@type": "GeoCoordinates",
    "latitude": 43.6328,
    "longitude": -113.306
  },
  "telephone": "+1 (208) 933-4115",
  "contactPoint": [

  ],
  "mainEntityOfPage": {
    "@Type": "Dataset",
    "id": "8401600212",
    "name": "us",
    "url": "http://www.imls.gov",
    "license": "http://creativecommons.org/licenses/by-sa/4.0/"
  }
}