{
  "@context": "http://schema.org",
  "@type": "Place",
  "additionalProperty": {
    "@type": "PropertyValue",
    "name": "id",
    "value": 130048
  },
  "name": "NTC FOUNDATIONS",
  "address": {
    "@type": "PostalAddress",
    "streetAddress": "2690 HISTORIC DECATUR RD",
    "addressLocality": "SAN DIEGO",
    "addressRegion": "CA",
    "addressCountry": "United States",
    "postalCode": "92106"
  },
  "hasMap": "http://www.openstreetmap.org/?mlat=32.7292&mlon=-117.221#map=15/32.7292/-117.221",
  "geo": {
    "@type": "GeoCoordinates",
    "latitude": 32.7292,
    "longitude": -117.221
  },
  "telephone": "+1 (619) 226-2506",
  "contactPoint": [

  ],
  "mainEntityOfPage": {
    "@Type": "Dataset",
    "id": "8400600174",
    "name": "us",
    "url": "http://www.imls.gov",
    "license": "http://creativecommons.org/licenses/by-sa/4.0/"
  }
}