{
  "@context": "http://schema.org",
  "@type": "Place",
  "additionalProperty": {
    "@type": "PropertyValue",
    "name": "id",
    "value": 130337
  },
  "name": [
    {
      "@value": "CULTURAL CENTER ROSECRUCIAN AMORC",
      "@language": "en"
    }
  ],
  "address": {
    "@type": "PostalAddress",
    "streetAddress": "6826 PINE AVE",
    "addressLocality": "BELL",
    "addressRegion": "CA",
    "addressCountry": "United States",
    "postalCode": "90201"
  },
  "hasMap": "http://www.openstreetmap.org/?mlat=33.9737&mlon=-118.189#map=15/33.9737/-118.189",
  "geo": {
    "@type": "GeoCoordinates",
    "latitude": 33.9737,
    "longitude": -118.189
  },
  "telephone": "+1 (323) 562-1516",
  "contactPoint": [

  ],
  "photo": {
    "@type": "ImageObject",
    "contentUrl": "http://images.museums.io/fNXgLn8BUiUuiHZhxGwOgaNhTXg=/1000x1000/museums/logos/000/130/337/original/Rc_planetarium.jpg",
    "creator": "No machine readable author provided. <a href=\"//commons.wikimedia.org/w/index.php?title=User:Zarathustra~commonswiki&amp;action=edit&amp;redlink=1\" class=\"new\" title=\"User:Zarathustra~commonswiki (page does not exist)\">Zarathustra~commonswiki</a> assumed (based on copyright claims).",
    "license": "https://creativecommons.org/licenses/by/2.5/"
  },
  "sameAs": "https://en.wikipedia.org/wiki/Rosicrucian_Park",
  "mainEntityOfPage": {
    "@Type": "Dataset",
    "id": "8400600463",
    "name": "us",
    "url": "http://www.imls.gov",
    "license": "http://creativecommons.org/licenses/by-sa/4.0/"
  }
}