{
  "@context": "http://schema.org",
  "@type": "Place",
  "additionalProperty": {
    "@type": "PropertyValue",
    "name": "id",
    "value": 155182
  },
  "name": [
    {
      "@value": "NORTHWESTERN PENNSYLVANIA RAILROADAND TOOLING HERITAGE CENTE",
      "@langauge": "en"
    }
  ],
  "address": {
    "@type": "PostalAddress",
    "streetAddress": "PO BOX 72",
    "addressLocality": "MEADVILLE",
    "addressRegion": "PA",
    "addressCountry": "United States",
    "postalCode": "16335-0072"
  },
  "hasMap": "http://www.openstreetmap.org/?mlat=41.6362&mlon=-80.1504#map=15/41.6362/-80.1504",
  "geo": {
    "@type": "GeoCoordinates",
    "latitude": 41.6362,
    "longitude": -80.1504
  },
  "mainEntityOfPage": {
    "@Type": "Dataset",
    "id": "8404200376",
    "name": "us",
    "url": "http://www.imls.gov",
    "license": "http://creativecommons.org/licenses/by-sa/4.0/"
  }
}