{
  "@context": "http://schema.org",
  "@type": "Place",
  "additionalProperty": {
    "@type": "PropertyValue",
    "name": "id",
    "value": 155547
  },
  "name": [
    {
      "@value": "OLD CALN MEETINGHOUSE",
      "@language": "en"
    }
  ],
  "address": {
    "@type": "PostalAddress",
    "streetAddress": "PO BOX 96",
    "addressLocality": "DOWNINGTOWN",
    "addressRegion": "PA",
    "addressCountry": "United States",
    "postalCode": "19335-0096"
  },
  "hasMap": "http://www.openstreetmap.org/?mlat=40.0184&mlon=-75.7151#map=15/40.0184/-75.7151",
  "geo": {
    "@type": "GeoCoordinates",
    "latitude": 40.0184,
    "longitude": -75.7151
  },
  "mainEntityOfPage": {
    "@Type": "Dataset",
    "id": "8404200741",
    "name": "us",
    "url": "http://www.imls.gov",
    "license": "http://creativecommons.org/licenses/by-sa/4.0/"
  }
}