{
  "@context": "http://schema.org",
  "@type": "Place",
  "additionalProperty": {
    "@type": "PropertyValue",
    "name": "id",
    "value": 155913
  },
  "name": [
    {
      "@value": "VENANGO MUSEUM OF ART SCIENCE AND INDUSTRY",
      "@language": "en"
    }
  ],
  "address": {
    "@type": "PostalAddress",
    "streetAddress": "270 SENECA ST",
    "addressLocality": "OIL CITY",
    "addressRegion": "PA",
    "addressCountry": "United States",
    "postalCode": "16301-1304"
  },
  "hasMap": "http://www.openstreetmap.org/?mlat=41.436&mlon=-79.709#map=15/41.436/-79.709",
  "geo": {
    "@type": "GeoCoordinates",
    "latitude": 41.436,
    "longitude": -79.709
  },
  "url": "http://www.venangomuseum.org",
  "telephone": "+1 (814) 676-2007",
  "mainEntityOfPage": {
    "@Type": "Dataset",
    "id": "8404201107",
    "name": "us",
    "url": "http://www.imls.gov",
    "license": "http://creativecommons.org/licenses/by-sa/4.0/"
  }
}