{
  "@context": "http://schema.org",
  "@type": "Place",
  "additionalProperty": {
    "@type": "PropertyValue",
    "name": "id",
    "value": 155967
  },
  "name": [
    {
      "@value": "BOALSBURG HERITAGE MUSEUM ASSOCIATION OF HARRIS TOWNSHIP",
      "@language": "en"
    }
  ],
  "address": {
    "@type": "PostalAddress",
    "streetAddress": "PO BOX 346",
    "addressLocality": "BOALSBURG",
    "addressRegion": "PA",
    "addressCountry": "United States",
    "postalCode": "16827-0346"
  },
  "hasMap": "http://www.openstreetmap.org/?mlat=40.7786&mlon=-77.7769#map=15/40.7786/-77.7769",
  "geo": {
    "@type": "GeoCoordinates",
    "latitude": 40.7786,
    "longitude": -77.7769
  },
  "url": "http://www.boalsburgheritagemuseum.org",
  "mainEntityOfPage": {
    "@Type": "Dataset",
    "id": "8404201161",
    "name": "us",
    "url": "http://www.imls.gov",
    "license": "http://creativecommons.org/licenses/by-sa/4.0/"
  }
}