{
  "@context": "http://schema.org",
  "@type": "Place",
  "additionalProperty": {
    "@type": "PropertyValue",
    "name": "id",
    "value": 188183
  },
  "name": [
    {
      "@value": "The Malacological Museum of Vieste",
      "@language": "en"
    },
    {
      "@value": "Museo malacologico di Vieste",
      "@language": "it"
    }
  ],
  "address": {
    "@type": "PostalAddress",
    "streetAddress": "Via Pola, 8",
    "addressLocality": "Vieste",
    "addressRegion": "Puglia",
    "addressCountry": "Italy"
  },
  "hasMap": "http://www.openstreetmap.org/?mlat=41.8833&mlon=16.1817#map=15/41.8833/16.1817",
  "geo": {
    "@type": "GeoCoordinates",
    "latitude": 41.8833,
    "longitude": 16.1817
  },
  "telephone": "+39 0884707688",
  "photo": {
    "@type": "ImageObject",
    "contentUrl": "http://images.museums.io/pz7GiHf0wAiu2XXVjKwLMK46ais=/1000x1000/museums/logos/000/188/183/original/f6fd926f5cb36cd9067ead6a47935804b6d3c6f.jpg"
  },
  "mainEntityOfPage": {
    "@Type": "Dataset",
    "id": "102391",
    "name": "itapi",
    "url": "http://www.beniculturali.it/mibac/export/MiBAC/sito-MiBAC/MenuPrincipale/Trasparenza/Open-Data/",
    "license": "http://creativecommons.org/licenses/by-sa/3.0/deed.it"
  }
}