{
  "@context": "http://schema.org",
  "@type": "Place",
  "additionalProperty": {
    "@type": "PropertyValue",
    "name": "id",
    "value": 188386
  },
  "name": [
    {
      "@value": "Museo civico delle ville storiche caltagironesi e siciliane",
      "@langauge": "it"
    }
  ],
  "address": {
    "@type": "PostalAddress",
    "streetAddress": "Via Santa Maria di Gesu', ",
    "addressLocality": "Caltagirone",
    "addressRegion": "Sicilia",
    "addressCountry": "Italy"
  },
  "telephone": "+39 093341831",
  "photo": {
    "@type": "ImageObject",
    "contentUrl": "http://images.museums.io/JBJmoeCSL0FdJGWVDF93b6drHvM=/1000x1000/museums/logos/000/188/386/original/59c29b1ebddf19f735b1397352643a5def654672.jpg"
  },
  "mainEntityOfPage": {
    "@Type": "Dataset",
    "id": "101189",
    "name": "itapi",
    "url": "http://www.beniculturali.it/mibac/export/MiBAC/sito-MiBAC/MenuPrincipale/Trasparenza/Open-Data/",
    "license": "http://creativecommons.org/licenses/by-sa/3.0/deed.it"
  }
}