{
  "@context": "http://schema.org",
  "@type": "Place",
  "additionalProperty": {
    "@type": "PropertyValue",
    "name": "id",
    "value": 188339
  },
  "name": [
    {
      "@value": "Museo dei minerali del monte Arci \"Stefano Incani\"",
      "@language": "it"
    }
  ],
  "address": {
    "@type": "PostalAddress",
    "streetAddress": "Piazza Convento, ",
    "addressLocality": "Masullas",
    "addressRegion": "Sardegna",
    "addressCountry": "Italy"
  },
  "hasMap": "http://www.openstreetmap.org/?mlat=39.7006&mlon=8.78376#map=15/39.7006/8.78376",
  "geo": {
    "@type": "GeoCoordinates",
    "latitude": 39.7006,
    "longitude": 8.78376
  },
  "url": "http://www.geomuseomontearci.it",
  "telephone": "+39 0783 990251 / 0783 996017",
  "photo": {
    "@type": "ImageObject",
    "contentUrl": "http://images.museums.io/-ZzqMIiddN7eHIyBFAWKmuWPnMQ=/1000x1000/museums/logos/000/188/339/original/5abcc73771853dcd28f722dc9b5fb45256ce700.JPG"
  },
  "mainEntityOfPage": {
    "@Type": "Dataset",
    "id": "105031",
    "name": "itapi",
    "url": "http://www.beniculturali.it/mibac/export/MiBAC/sito-MiBAC/MenuPrincipale/Trasparenza/Open-Data/",
    "license": "http://creativecommons.org/licenses/by-sa/3.0/deed.it"
  }
}