{
  "@context": "http://schema.org",
  "@type": "Place",
  "additionalProperty": {
    "@type": "PropertyValue",
    "name": "id",
    "value": 182840
  },
  "name": [
    {
      "@value": "Museum für Archäologie und Gemeindegeschichte Gutenstetten",
      "@language": "en"
    }
  ],
  "address": {
    "@type": "PostalAddress",
    "streetAddress": "Hauptstraße 32",
    "addressLocality": "Gutenstetten",
    "addressRegion": "Mittelfranken",
    "addressCountry": "Germany",
    "postalCode": "91468"
  },
  "hasMap": "http://www.openstreetmap.org/?mlat=49.6182&mlon=10.6294#map=15/49.6182/10.6294",
  "geo": {
    "@type": "GeoCoordinates",
    "latitude": 49.6182,
    "longitude": 10.6294
  },
  "url": "http://www.gutenstetten.de/index.php?s=62&text=Museum",
  "telephone": "09161/3167",
  "mainEntityOfPage": {
    "@Type": "Dataset",
    "name": "de_bavaria",
    "url": "http://www.museums.io/en/museums/182840",
    "license": "http://creativecommons.org/licenses/by-sa/4.0/"
  }
}