{
  "@context": "http://schema.org",
  "@type": "Place",
  "additionalProperty": {
    "@type": "PropertyValue",
    "name": "id",
    "value": 182977
  },
  "name": [
    {
      "@value": "Archäologisches Museum der Stadt Kelheim",
      "@language": "en"
    }
  ],
  "address": {
    "@type": "PostalAddress",
    "streetAddress": "Lederergasse 11",
    "addressLocality": "Kelheim",
    "addressRegion": "Niederbayern",
    "addressCountry": "Germany",
    "postalCode": "93309"
  },
  "hasMap": "http://www.openstreetmap.org/?mlat=48.9176&mlon=11.8704#map=15/48.9176/11.8704",
  "geo": {
    "@type": "GeoCoordinates",
    "latitude": 48.9176,
    "longitude": 11.8704
  },
  "url": "http://www.archaeologisches-museum-kelheim.de",
  "telephone": "09441/10492",
  "mainEntityOfPage": {
    "@Type": "Dataset",
    "name": "de_bavaria",
    "url": "http://www.museums.io/en/museums/182977",
    "license": "http://creativecommons.org/licenses/by-sa/4.0/"
  }
}