{
  "@context": "http://schema.org",
  "@type": "Place",
  "additionalProperty": {
    "@type": "PropertyValue",
    "name": "id",
    "value": 162662
  },
  "name": "ELLISON BAY POTTERY",
  "address": {
    "@type": "PostalAddress",
    "streetAddress": "12156 GARRETT BAY RD",
    "addressLocality": "ELLISON BAY",
    "addressRegion": "WI",
    "addressCountry": "United States",
    "postalCode": "54210"
  },
  "hasMap": "http://www.openstreetmap.org/?mlat=45.2604&mlon=-87.0705#map=15/45.2604/-87.0705",
  "geo": {
    "@type": "GeoCoordinates",
    "latitude": 45.2604,
    "longitude": -87.0705
  },
  "url": "http://ellisonbaypottery.wordpress.com",
  "telephone": "+1 (920) 854-5049",
  "contactPoint": [

  ],
  "mainEntityOfPage": {
    "@Type": "Dataset",
    "id": "8405500111",
    "name": "us",
    "url": "http://www.imls.gov",
    "license": "http://creativecommons.org/licenses/by-sa/4.0/"
  }
}