{
  "@context": "http://schema.org",
  "@type": "Place",
  "additionalProperty": {
    "@type": "PropertyValue",
    "name": "id",
    "value": 151466
  },
  "name": [
    {
      "@value": "FREMONT HISTORICAL MUSEUM & PRESERVATION SOCIETY",
      "@langauge": "en"
    }
  ],
  "address": {
    "@type": "PostalAddress",
    "streetAddress": "PO BOX 222",
    "addressLocality": "FREMONT",
    "addressRegion": "NC",
    "addressCountry": "United States",
    "postalCode": "27830-0222"
  },
  "hasMap": "http://www.openstreetmap.org/?mlat=35.5496&mlon=-77.9652#map=15/35.5496/-77.9652",
  "geo": {
    "@type": "GeoCoordinates",
    "latitude": 35.5496,
    "longitude": -77.9652
  },
  "mainEntityOfPage": {
    "@Type": "Dataset",
    "id": "8403700337",
    "name": "us",
    "url": "http://www.imls.gov",
    "license": "http://creativecommons.org/licenses/by-sa/4.0/"
  }
}