{
  "@context": "http://schema.org",
  "@type": "Place",
  "additionalProperty": {
    "@type": "PropertyValue",
    "name": "id",
    "value": 162858
  },
  "name": "ZOOLOGICAL SOCIETY OF KEWAUNEE COUNTY INC",
  "address": {
    "@type": "PostalAddress",
    "streetAddress": "E4280 CTH F",
    "addressLocality": "KEWAUNEE",
    "addressRegion": "WI",
    "addressCountry": "United States",
    "postalCode": "54216"
  },
  "hasMap": "http://www.openstreetmap.org/?mlat=44.4569&mlon=-87.5241#map=15/44.4569/-87.5241",
  "geo": {
    "@type": "GeoCoordinates",
    "latitude": 44.4569,
    "longitude": -87.5241
  },
  "contactPoint": [

  ],
  "mainEntityOfPage": {
    "@Type": "Dataset",
    "id": "8405500307",
    "name": "us",
    "url": "http://www.imls.gov",
    "license": "http://creativecommons.org/licenses/by-sa/4.0/"
  }
}