{
  "@context": "http://schema.org",
  "@type": "Place",
  "additionalProperty": {
    "@type": "PropertyValue",
    "name": "id",
    "value": 145456
  },
  "name": "1699 HISTORICAL SOCIETY",
  "address": {
    "@type": "PostalAddress",
    "streetAddress": "PO BOX 713",
    "addressLocality": "OCEAN SPRINGS",
    "addressRegion": "MS",
    "addressCountry": "United States",
    "postalCode": "39566"
  },
  "hasMap": "http://www.openstreetmap.org/?mlat=30.4162&mlon=-88.8214#map=15/30.4162/-88.8214",
  "geo": {
    "@type": "GeoCoordinates",
    "latitude": 30.4162,
    "longitude": -88.8214
  },
  "url": "http://www.1699landing.org",
  "contactPoint": [

  ],
  "mainEntityOfPage": {
    "@Type": "Dataset",
    "id": "8402800163",
    "name": "us",
    "url": "http://www.imls.gov",
    "license": "http://creativecommons.org/licenses/by-sa/4.0/"
  }
}