{
  "@context": "http://schema.org",
  "@type": "Place",
  "additionalProperty": {
    "@type": "PropertyValue",
    "name": "id",
    "value": 145915
  },
  "name": "LAUMEIER SCULPTURE PARK",
  "address": {
    "@type": "PostalAddress",
    "streetAddress": "12580 ROTT RD",
    "addressLocality": "SAINT LOUIS",
    "addressRegion": "MO",
    "addressCountry": "United States",
    "postalCode": "63127-1212"
  },
  "hasMap": "http://www.openstreetmap.org/?mlat=38.552&mlon=-90.4123#map=15/38.552/-90.4123",
  "geo": {
    "@type": "GeoCoordinates",
    "latitude": 38.552,
    "longitude": -90.4123
  },
  "url": "http://www.laumeier.org",
  "telephone": "+1 (314) 615-5278",
  "contactPoint": [

  ],
  "mainEntityOfPage": {
    "@Type": "Dataset",
    "id": "8402900344",
    "name": "us",
    "url": "http://www.imls.gov",
    "license": "http://creativecommons.org/licenses/by-sa/4.0/"
  }
}