{
  "@context": "http://schema.org",
  "@type": "Place",
  "additionalProperty": {
    "@type": "PropertyValue",
    "name": "id",
    "value": 159454
  },
  "name": [
    {
      "@value": "ITASCA HISTORICAL & INVESTMENT COUNCIL INC",
      "@language": "en"
    }
  ],
  "address": {
    "@type": "PostalAddress",
    "streetAddress": "PO BOX 127",
    "addressLocality": "ITASCA",
    "addressRegion": "TX",
    "addressCountry": "United States",
    "postalCode": "76055"
  },
  "hasMap": "http://www.openstreetmap.org/?mlat=32.1587&mlon=-97.1497#map=15/32.1587/-97.1497",
  "geo": {
    "@type": "GeoCoordinates",
    "latitude": 32.1587,
    "longitude": -97.1497
  },
  "mainEntityOfPage": {
    "@Type": "Dataset",
    "id": "8404801554",
    "name": "us",
    "url": "http://www.imls.gov",
    "license": "http://creativecommons.org/licenses/by-sa/4.0/"
  }
}