{
  "@context": "http://schema.org",
  "@type": "Place",
  "additionalProperty": {
    "@type": "PropertyValue",
    "name": "id",
    "value": 143166
  },
  "name": [
    {
      "@value": "BOSTON FIRE HISTORICAL SOCIETY INC",
      "@langauge": "en"
    }
  ],
  "address": {
    "@type": "PostalAddress",
    "streetAddress": "PO BOX 347",
    "addressLocality": "READVILLE",
    "addressRegion": "MA",
    "addressCountry": "United States",
    "postalCode": "02137"
  },
  "hasMap": "http://www.openstreetmap.org/?mlat=42.2378&mlon=-71.1316#map=15/42.2378/-71.1316",
  "geo": {
    "@type": "GeoCoordinates",
    "latitude": 42.2378,
    "longitude": -71.1316
  },
  "url": "http://www.bostonfirehistory.org",
  "mainEntityOfPage": {
    "@Type": "Dataset",
    "id": "8402500796",
    "name": "us",
    "url": "http://www.imls.gov",
    "license": "http://creativecommons.org/licenses/by-sa/4.0/"
  }
}