{
  "@context": "http://schema.org",
  "@type": "Place",
  "additionalProperty": {
    "@type": "PropertyValue",
    "name": "id",
    "value": 143611
  },
  "name": [
    {
      "@value": "GRATTAN MUSEUM",
      "@langauge": "en"
    }
  ],
  "address": {
    "@type": "PostalAddress",
    "streetAddress": "12040 BELDING RD NE",
    "addressLocality": "BELDING",
    "addressRegion": "MI",
    "addressCountry": "United States",
    "postalCode": "48809"
  },
  "hasMap": "http://www.openstreetmap.org/?mlat=43.0826&mlon=-85.3691#map=15/43.0826/-85.3691",
  "geo": {
    "@type": "GeoCoordinates",
    "latitude": 43.0826,
    "longitude": -85.3691
  },
  "telephone": "+1 (616) 691-6504",
  "mainEntityOfPage": {
    "@Type": "Dataset",
    "id": "8402600148",
    "name": "us",
    "url": "http://www.imls.gov",
    "license": "http://creativecommons.org/licenses/by-sa/4.0/"
  }
}