{
  "@context": "http://schema.org",
  "@type": "Place",
  "additionalProperty": {
    "@type": "PropertyValue",
    "name": "id",
    "value": 149245
  },
  "name": "BROOKLYN BOTANIC GARDEN CORPORATION",
  "address": {
    "@type": "PostalAddress",
    "streetAddress": "1000 WASHINGTON AVE",
    "addressLocality": "BROOKLYN",
    "addressRegion": "NY",
    "addressCountry": "United States",
    "postalCode": "11225-1008"
  },
  "hasMap": "http://www.openstreetmap.org/?mlat=40.6669&mlon=-73.9616#map=15/40.6669/-73.9616",
  "geo": {
    "@type": "GeoCoordinates",
    "latitude": 40.6669,
    "longitude": -73.9616
  },
  "url": "http://www.bbg.org",
  "contactPoint": [

  ],
  "mainEntityOfPage": {
    "@Type": "Dataset",
    "id": "8403600539",
    "name": "us",
    "url": "http://www.imls.gov",
    "license": "http://creativecommons.org/licenses/by-sa/4.0/"
  }
}