{
  "@context": "http://schema.org",
  "@type": "Place",
  "additionalProperty": {
    "@type": "PropertyValue",
    "name": "id",
    "value": 149563
  },
  "name": [
    {
      "@value": "HAVERSTRAW SPORTS HALL OF FAME INC. NORTH ROCKLAND SPORTS HA",
      "@langauge": "en"
    }
  ],
  "address": {
    "@type": "PostalAddress",
    "streetAddress": "C/O NORTH ROCKLAND HIGH SCHOOL HAMM",
    "addressLocality": "THIELLS",
    "addressRegion": "NY",
    "addressCountry": "United States",
    "postalCode": "10984"
  },
  "hasMap": "http://www.openstreetmap.org/?mlat=41.2071&mlon=-74.0227#map=15/41.2071/-74.0227",
  "geo": {
    "@type": "GeoCoordinates",
    "latitude": 41.2071,
    "longitude": -74.0227
  },
  "mainEntityOfPage": {
    "@Type": "Dataset",
    "id": "8403600857",
    "name": "us",
    "url": "http://www.imls.gov",
    "license": "http://creativecommons.org/licenses/by-sa/4.0/"
  }
}