{
  "@context": "http://schema.org",
  "@type": "Place",
  "additionalProperty": {
    "@type": "PropertyValue",
    "name": "id",
    "value": 129714
  },
  "name": [
    {
      "@value": "UNIVERSITY OF ARKANSAS",
      "@language": "en"
    }
  ],
  "address": {
    "@type": "PostalAddress",
    "streetAddress": "2801 S UNIVERSITY AVE",
    "addressLocality": "LITTLE ROCK",
    "addressRegion": "AR",
    "addressCountry": "United States",
    "postalCode": "72204"
  },
  "hasMap": "http://www.openstreetmap.org/?mlat=34.7269&mlon=-92.3418#map=15/34.7269/-92.3418",
  "geo": {
    "@type": "GeoCoordinates",
    "latitude": 34.7269,
    "longitude": -92.3418
  },
  "mainEntityOfPage": {
    "@Type": "Dataset",
    "id": "8400500150",
    "name": "us",
    "url": "http://www.imls.gov",
    "license": "http://creativecommons.org/licenses/by-sa/4.0/"
  }
}