{
  "@context": "http://schema.org",
  "@type": "Place",
  "additionalProperty": {
    "@type": "PropertyValue",
    "name": "id",
    "value": 163353
  },
  "name": "FRIENDS OF STONEFIELD STATE HISTORIC SITE & NELSON DEWEY STA",
  "address": {
    "@type": "PostalAddress",
    "streetAddress": "PO BOX 658",
    "addressLocality": "CASSVILLE",
    "addressRegion": "WI",
    "addressCountry": "United States",
    "postalCode": "53806-0658"
  },
  "hasMap": "http://www.openstreetmap.org/?mlat=42.7174&mlon=-90.9327#map=15/42.7174/-90.9327",
  "geo": {
    "@type": "GeoCoordinates",
    "latitude": 42.7174,
    "longitude": -90.9327
  },
  "contactPoint": [

  ],
  "mainEntityOfPage": {
    "@Type": "Dataset",
    "id": "8405500802",
    "name": "us",
    "url": "http://www.imls.gov",
    "license": "http://creativecommons.org/licenses/by-sa/4.0/"
  }
}