{
  "@context": "http://schema.org",
  "@type": "Place",
  "additionalProperty": {
    "@type": "PropertyValue",
    "name": "id",
    "value": 156659
  },
  "name": "NARRAGANSETT FIREMENS MUSEUM INCORPORATED",
  "address": {
    "@type": "PostalAddress",
    "streetAddress": "PO BOX 283",
    "addressLocality": "NARRAGANSETT",
    "addressRegion": "RI",
    "addressCountry": "United States",
    "postalCode": "02882"
  },
  "hasMap": "http://www.openstreetmap.org/?mlat=41.4963&mlon=-71.3705#map=15/41.4963/-71.3705",
  "geo": {
    "@type": "GeoCoordinates",
    "latitude": 41.4963,
    "longitude": -71.3705
  },
  "url": "http://jamestownfd.com/museum.html",
  "telephone": "+1 (401) 423-0062",
  "contactPoint": [

  ],
  "mainEntityOfPage": {
    "@Type": "Dataset",
    "id": "8404400163",
    "name": "us",
    "url": "http://www.imls.gov",
    "license": "http://creativecommons.org/licenses/by-sa/4.0/"
  }
}