{
  "@context": "http://schema.org",
  "@type": "Place",
  "additionalProperty": {
    "@type": "PropertyValue",
    "name": "id",
    "value": 140731
  },
  "name": "SHREVEPORT WATER WORKS MUSEUM",
  "address": {
    "@type": "PostalAddress",
    "streetAddress": "142 N COMMON ST",
    "addressLocality": "SHREVEPORT",
    "addressRegion": "LA",
    "addressCountry": "United States",
    "postalCode": "71101"
  },
  "hasMap": "http://www.openstreetmap.org/?mlat=32.5144&mlon=-93.7559#map=15/32.5144/-93.7559",
  "geo": {
    "@type": "GeoCoordinates",
    "latitude": 32.5144,
    "longitude": -93.7559
  },
  "url": "http://www.mcneillstreet.org",
  "telephone": "+1 (318) 221-3388",
  "contactPoint": [

  ],
  "mainEntityOfPage": {
    "@Type": "Dataset",
    "id": "8402200013",
    "name": "us",
    "url": "http://www.imls.gov",
    "license": "http://creativecommons.org/licenses/by-sa/4.0/"
  }
}