{
  "@context": "http://schema.org",
  "@type": "Place",
  "additionalProperty": {
    "@type": "PropertyValue",
    "name": "id",
    "value": 157144
  },
  "name": [
    {
      "@value": "LANTIS ENTERPRISES",
      "@language": "en"
    }
  ],
  "address": {
    "@type": "PostalAddress",
    "streetAddress": "4755 E COLORADO BLVD",
    "addressLocality": "SPEARFISH",
    "addressRegion": "SD",
    "addressCountry": "United States",
    "postalCode": "57783"
  },
  "hasMap": "http://www.openstreetmap.org/?mlat=44.4743&mlon=-103.765#map=15/44.4743/-103.765",
  "geo": {
    "@type": "GeoCoordinates",
    "latitude": 44.4743,
    "longitude": -103.765
  },
  "url": "http://www.lantisnet.com",
  "telephone": "+1 (605) 642-7736",
  "mainEntityOfPage": {
    "@Type": "Dataset",
    "id": "8404600029",
    "name": "us",
    "url": "http://www.imls.gov",
    "license": "http://creativecommons.org/licenses/by-sa/4.0/"
  }
}