{
  "@context": "http://schema.org",
  "@type": "Place",
  "additionalProperty": {
    "@type": "PropertyValue",
    "name": "id",
    "value": 144409
  },
  "name": "HISTORICAL PRESERVATION SOCIETY OF DUNDEE",
  "address": {
    "@type": "PostalAddress",
    "streetAddress": "242 TOLDEO STREET",
    "addressLocality": "DUNDEE",
    "addressRegion": "MI",
    "addressCountry": "United States",
    "postalCode": "48131"
  },
  "hasMap": "http://www.openstreetmap.org/?mlat=41.9558&mlon=-83.6587#map=15/41.9558/-83.6587",
  "geo": {
    "@type": "GeoCoordinates",
    "latitude": 41.9558,
    "longitude": -83.6587
  },
  "url": "http://www.dundeeoldmill.com",
  "contactPoint": [

  ],
  "mainEntityOfPage": {
    "@Type": "Dataset",
    "id": "8402600946",
    "name": "us",
    "url": "http://www.imls.gov",
    "license": "http://creativecommons.org/licenses/by-sa/4.0/"
  }
}