{
  "@context": "http://schema.org",
  "@type": "Place",
  "additionalProperty": {
    "@type": "PropertyValue",
    "name": "id",
    "value": 143799
  },
  "name": "CLARKSTON COMMUNITY HISTORICAL SOCIETY",
  "address": {
    "@type": "PostalAddress",
    "streetAddress": "6495 CLARKSTON RD",
    "addressLocality": "CLARKSTON",
    "addressRegion": "MI",
    "addressCountry": "United States",
    "postalCode": "48346-1501"
  },
  "hasMap": "http://www.openstreetmap.org/?mlat=42.7402&mlon=-83.4088#map=15/42.7402/-83.4088",
  "geo": {
    "@type": "GeoCoordinates",
    "latitude": 42.7402,
    "longitude": -83.4088
  },
  "url": "http://www.clarkstonhistorical.org",
  "telephone": "+1 (248) 922-0270",
  "contactPoint": [

  ],
  "mainEntityOfPage": {
    "@Type": "Dataset",
    "id": "8402600336",
    "name": "us",
    "url": "http://www.imls.gov",
    "license": "http://creativecommons.org/licenses/by-sa/4.0/"
  }
}